odoo/addons/payment_pagseguro/README.rst
odoo/addons/payment_pagseguro/__init__.py
odoo/addons/payment_pagseguro/__manifest__.py
odoo/addons/payment_pagseguro/controllers/__init__.py
odoo/addons/payment_pagseguro/controllers/main.py
odoo/addons/payment_pagseguro/data/payment_acquirer_data.xml
odoo/addons/payment_pagseguro/i18n/payment_pagseguro.pot
odoo/addons/payment_pagseguro/i18n/pt_BR.po
odoo/addons/payment_pagseguro/models/__init__.py
odoo/addons/payment_pagseguro/models/payment_acquirer.py
odoo/addons/payment_pagseguro/models/payment_token.py
odoo/addons/payment_pagseguro/models/payment_transaction.py
odoo/addons/payment_pagseguro/readme/CONFIGURE.rst
odoo/addons/payment_pagseguro/readme/CONTRIBUTORS.rst
odoo/addons/payment_pagseguro/readme/CREDITS.rst
odoo/addons/payment_pagseguro/readme/DESCRIPTION.rst
odoo/addons/payment_pagseguro/readme/HISTORY.rst
odoo/addons/payment_pagseguro/readme/INSTALL.rst
odoo/addons/payment_pagseguro/readme/ROADMAP.rst
odoo/addons/payment_pagseguro/readme/USAGE.rst
odoo/addons/payment_pagseguro/static/description/icon.png
odoo/addons/payment_pagseguro/static/description/index.html
odoo/addons/payment_pagseguro/static/description/pagseguro_buy.png
odoo/addons/payment_pagseguro/static/description/pagseguro_website.png
odoo/addons/payment_pagseguro/static/description/payment_acquirer_01.png
odoo/addons/payment_pagseguro/static/description/payment_acquirer_02.png
odoo/addons/payment_pagseguro/static/src/img/pag_seguro_icon.jpg
odoo/addons/payment_pagseguro/static/src/js/pagseguro_tokenize_card.js
odoo/addons/payment_pagseguro/static/src/js/pagseguro_tour.js
odoo/addons/payment_pagseguro/tests/__init__.py
odoo/addons/payment_pagseguro/tests/test_pagseguro.py
odoo/addons/payment_pagseguro/tests/fixtures/test_buy_pagseguro.yaml
odoo/addons/payment_pagseguro/tests/fixtures/test_buy_pagseguro_fail.yaml
odoo/addons/payment_pagseguro/views/payment_acquirer.xml
odoo/addons/payment_pagseguro/views/payment_pagseguro_templates.xml
odoo14_addon_payment_pagseguro-14.0.1.0.12.dist-info/METADATA
odoo14_addon_payment_pagseguro-14.0.1.0.12.dist-info/WHEEL
odoo14_addon_payment_pagseguro-14.0.1.0.12.dist-info/top_level.txt
odoo14_addon_payment_pagseguro-14.0.1.0.12.dist-info/RECORD
