Metadata-Version: 2.1
Name: odoo14-addon-payment_pagseguro
Version: 14.0.1.0.12
Summary: Payment Acquirer: PagSeguro Implementation
Home-page: https://github.com/OCA/l10n-brazil
Author: KMEE, Odoo Community Association (OCA)
Author-email: support@odoo-community.org
License: AGPL-3
Classifier: Programming Language :: Python
Classifier: Framework :: Odoo
Classifier: Framework :: Odoo :: 14.0
Classifier: License :: OSI Approved :: GNU Affero General Public License v3
Requires-Python: >=3.6
Requires-Dist: odoo<14.1dev,>=14.0a
